examples/__init__.py
examples/directory/__init__.py
examples/directory/delete_deletedObjects.py
examples/directory/import_users.py
examples/onedrive/__init__.py
examples/onedrive/export_files.py
examples/onedrive/import_files.py
examples/onedrive/print_folders_and_files.py
examples/outlook/__init__.py
examples/outlook/send_message.py
examples/sharepoint/__init__.py
examples/sharepoint/connect_with_app.py
examples/sharepoint/connect_with_azure_app.py
examples/sharepoint/connect_with_proxy.py
examples/sharepoint/connect_with_user_creds.py
examples/sharepoint/export_search_crawl_log.py
examples/sharepoint/load_web_fluent_api.py
examples/sharepoint/read_resource_no_model.py
examples/sharepoint/admin/__init__.py
examples/sharepoint/audit/__init__.py
examples/sharepoint/export/__init__.py
examples/sharepoint/export/exportList.py
examples/sharepoint/files/__init__.py
examples/sharepoint/files/download_file.py
examples/sharepoint/files/download_file_from_url.py
examples/sharepoint/files/upload_file.py
examples/sharepoint/files/upload_large_file.py
examples/sharepoint/folders/__init__.py
examples/sharepoint/folders/download_folder.py
examples/sharepoint/import/__init__.py
examples/sharepoint/lists_and_items/__init__.py
examples/sharepoint/lists_and_items/data_generator.py
examples/sharepoint/lists_and_items/read_attachments.py
examples/sharepoint/lists_and_items/read_large_list.py
examples/sharepoint/search/__init__.py
examples/sharepoint/search/search_documents.py
examples/teams/__init__.py
examples/teams/provision_team.py
generator/__init__.py
generator/generate.py
generator/typeBuilder.py
generator/templates/__init__.py
office365/__init__.py
office365/logger.py
office365/graph/__init__.py
office365/graph/base_item.py
office365/graph/entity.py
office365/graph/graph_client.py
office365/graph/one_drive_actions.py
office365/graph/resource_path_url.py
office365/graph/contacts/__init__.py
office365/graph/directory/__init__.py
office365/graph/directory/auditActivityInitiator.py
office365_rest_client-2.2.0.dist-info/LICENSE
office365_rest_client-2.2.0.dist-info/METADATA
office365_rest_client-2.2.0.dist-info/WHEEL
office365_rest_client-2.2.0.dist-info/top_level.txt
office365_rest_client-2.2.0.dist-info/RECORD
