Metadata-Version: 2.1
Name: office365-rest-client
Version: 2.2.0
Summary: Office 365 Library for Python
Home-page: https://github.com/vgrem/Office365-REST-Python-Client
Author: Vadim Gremyachev
Author-email: vvgrem@gmail.com
Maintainer: Konrad Gądek
Maintainer-email: kgadek@gmail.com
License: MIT
Keywords: git
Platform: UNKNOWN
Classifier: Development Status :: 4 - Beta
Classifier: Intended Audience :: Developers
Classifier: License :: OSI Approved :: MIT License
Classifier: Topic :: Internet :: WWW/HTTP
Classifier: Topic :: Software Development :: Libraries
Classifier: Programming Language :: Python
Classifier: Programming Language :: Python :: 2
Classifier: Programming Language :: Python :: 2.7
Classifier: Programming Language :: Python :: 3
Classifier: Programming Language :: Python :: 3.5
Classifier: Programming Language :: Python :: 3.6
Classifier: Programming Language :: Python :: 3.7
Classifier: Programming Language :: Python :: 3.8
Provides-Extra: NTLMAuthentication
